rise_set/__init__.py
rise_set/angle.py
rise_set/astrometry.py
rise_set/logging.conf
rise_set/moving_objects.py
rise_set/rates.py
rise_set/sky_coordinates.py
rise_set/transits.py
rise_set/utils.py
rise_set/visibility.py
rise_set-0.4.12.dist-info/METADATA
rise_set-0.4.12.dist-info/WHEEL
rise_set-0.4.12.dist-info/dependency_links.txt
rise_set-0.4.12.dist-info/top_level.txt
rise_set-0.4.12.dist-info/RECORD
