Metadata-Version: 2.1
Name: rise-set
Version: 0.4.12
Summary: Routines for accurate rise/set/transit calculations
Home-page: UNKNOWN
Author: Eric Saunders
Author-email: esaunders@lcogt.net
License: UNKNOWN
Platform: UNKNOWN
Classifier: Programming Language :: Python :: 2.7
Classifier: Programming Language :: Python :: 3.3
Requires-Dist: pySLALIB
Requires-Dist: numpy
Requires-Dist: future
